Workbook

Sheet README
A1: CREDIT RISK DATA PROGRAMME — TRACKER WORKBOOK
A2: Companion to D:\Tools\credit_risk_data\credit_risk_data_landscape.md (v2, 30-Jul-2026). Built 30-Jul-2026.
A4: PURPOSE
A5: A living checklist of everything planned: data sources to fetch, datasets to assemble, pipelines to build,
A6: model prototypes, database landing places, calibration anchors, licensing constraints and open items.
A7: Tick statuses as you progress; the Dashboard recomputes automatically.
A9: SHEETS
A10: Dashboard — live progress KPIs (formulas; do not type over)
A11: 1_Sources — master source checklist (108 sources: what, where, access, backfill, DB target)
A12: 2_Assembly — 7 flagship datasets to assemble (IBBI LGD, India default corpus, NBFC ECL panel, P3DH panel, district panel, anchor warehouse, synthetic books)
A13: 3_Prototypes — 12 model prototypes with their Layer-1/Layer-2 data stacks
A14: 4_Pipelines — 32 fetch/parse/load engineering tasks with anti-bot notes
... A24: 4. Statuses colour themselves: green = landed, amber = in flight, red = blocked, grey = not started.
A25: 5. Research/verification phase is COMPLETE (landscape doc v2). This workbook tracks the BUILD phase. | B25: ID | C25: Source | D25: Priority | E25: Status | F25: Backfill plan | G25: DB target | H25: Notes
B26: S-001 | C26: Freddie Mac SFLLD | D26: P1 | E26: Fetched | F26: 1999-2025 full, sample file first | G26: micro.facility_master | H26: Downloaded 2026-08-02; 2 vintages parsed
A27: EXAMPLE ROW (how a filled Sources row should look)
A31: STATUS DEFINITIONS
A32: Fetched = raw files landed locally. Cleaned = parsed/normalized. Loaded = in the database target.
A33: Validated = QA'd against anchors (6_Anchors) or published totals. Done = fully operational incl. refresh.
A35: PROVENANCE
A36: All content compiled from credit_risk_data_landscape.md v2 (five-workstream verified research pass, 30-Jul-2026).
A37: Numbers in 6_Anchors carry their as-of dates and sources; items flagged in 8_Watchlist were NOT verified — check before load-bearing use.
A39: CHANGELOG
A40: 2026-07-30 Workbook created (research v1+v2 complete; build phase not started).

Sheet 1_Sources
A1: 1. DATA SOURCES — master checklist
A2: One row per source. Tick 'Status' as you progress; edit yellow-headed columns. Compiled 30-Jul-2026 from credit_risk_data_landscape.md v2.
A3: ID | B3: Region | C3: Category | D3: Source | E3: Publisher | F3: Portfolio(s) | G3: Use for | H3: Granularity | I3: Frequency | J3: Coverage / history | K3: Access | L3: Fetch method | M3: Backfill plan | N3: Refresh cadence | O3: Priority | P3: Status | Q3: DB target | R3: License notes | S3: URL | T3: Notes
A4: S-001 | B4: Global | C4: Loan-level micro | D4: Freddie Mac Single-Family Loan-Level Dataset | E4: Freddie Mac | F4: Mortgage | G4: PD, LGD, prepayment, cure, ECL | H4: Loan-month panel | I4: Quarterly release | J4: 1999-Sep 2025, ~55M loans | K4: Registration | L4: Bulk ZIP download | M4: Full history once (subset vintages first) | N4: Quarterly | O4: P1 | P4: Not started | Q4: micro.facility_master + micro.performance_monthly + micro.recovery_cashflows | R4: No redistribution | S4: freddiemac.com | T4: Expense & proceeds columns make it LGD-capable; canonical prepayment data
A5: S-002 | B5: Global | C5: Loan-level micro | D5: Fannie Mae SF Loan Performance (CAS enhanced) | E5: Fannie Mae | F5: Mortgage | G5: PD, LGD, prepayment | H5: Loan-month panel | I5: Quarterly release | J5: 2000+ | K5: Registration | L5: Bulk download | M5: Full once | N5: Quarterly | O5: P2 | P5: Not started | Q5: micro.* (same as Freddie) | R5: No redistribution | S5: capitalmarkets.fanniemae.com | T5: Credit-event costs and recovery proceeds through disposition
A6: S-003 | B6: Global | C6: Loan-level micro | D6: Ginnie Mae MBS loan-level disclosure | E6: Ginnie Mae | F6: Mortgage (govt) | G6: PD, delinquency | H6: Loan-month | I6: Monthly | J6: 2012+ | K6: Open | L6: Bulk download | M6: Optional | N6: Monthly | O6: P3 | P6: Not started | Q6: micro.* | R6: Open | S6: ginniemae.gov | T6: FHA/VA credit box - contrast portfolio
A7: S-004 | B7: Global | C7: Loan-level micro | D7: GSE Multifamily (Freddie MLPD + Fannie MF) | E7: Freddie/Fannie | F7: CRE multifamily | G7: PD, LGD | H7: Loan-level | I7: Periodic | J7: 1994+ | K7: Registration | L7: Download | M7: Full once | N7: Annual | O7: P3 | P7: Not started | Q7: micro.* | R7: No redistribution | S7: mf.freddiemac.com | T7: Includes REO sale dates
A8: S-005 | B8: Global | C8: Collateral index | D8: FHFA HPI + NMDB aggregate statistics | E8: FHFA | F8: Mortgage collateral | G8: LGD collateral paths, performance aggregates | H8: Index: national to ZIP | I8: Quarterly/monthly | J8: Mid-1970s+ | K8: Open | L8: CSV/API | M8: Full once | N8: Quarterly | O8: P1 | P8: Not started | Q8: idx.collateral_indices | R8: Public domain | S8: fhfa.gov | T8: Drives mortgage LGD stress
A9: S-006 | B9: Global | C9: Loan-level micro | D9: HMDA LAR (incl. declined applications) | E9: FFIEC/CFPB | F9: Mortgage | G9: Scorecard inputs, reject inference | H9: Application-level | I9: Annual | J9: 2007+ (modern format 2018+) | K9: Open | L9: Bulk CSV | M9: Selected years | N9: Annual | O9: P2 | P9: Not started | Q9: micro.applications | R9: Public | S9: ffiec.cfpb.gov | T9: One of very few public sources of rejects
A10: S-007 | B10: Global | C10: Loan-level micro | D10: SEC ABS-EE auto loan/lease EX-102 files | E10: Issuers via SEC EDGAR | F10: Auto | G10: PD, LGD, recovery timing | H10: Loan-month XML | I10: Monthly per deal | J10: Nov 2016+ | K10: Open | L10: EDGAR scrape + XML parse | M10: Backfill all major shelves | N10: Monthly | O10: P1 | P10: Not started | Q10: micro.facility_master + micro.recovery_cashflows | R10: Public | S10: efts.sec.gov | T10: Charge-off AND recovery amounts; Ford/GM/Santander/CarMax/Carvana/Westlake
A11: S-008 | B11: Global | C11: Loan-level micro | D11: CMBS ABS-EE / CREFC IRP servicer data | E11: Issuers via SEC EDGAR | F11: CRE | G11: PD, LGD | H11: Loan-level | I11: Monthly | J11: 2016+ | K11: Open | L11: XML parse | M11: Optional | N11: Monthly | O11: P3 | P11: Not started | Q11: micro.* | R11: Public | S11: sec.gov | T11: Rich but lower priority vs India focus
A12: S-009 | B12: Global | C12: Pool-level | D12: Credit card master trust 10-D reports | E12: Chase/Citi/COF/Amex via EDGAR | F12: Cards | G12: Vintage stress, roll rates, payment rate (EAD proxy) | H12: Pool-month | I12: Monthly | J12: ~2000+ | K12: Open | L12: EDGAR scrape + table parse | M12: 20y backfill | N12: Monthly | O12: P1 | P12: Not started | Q12: agg.card_trust_series | R12: Public | S12: sec.gov | T12: Charge-off, 30-180+ buckets, monthly payment rate, yield, excess spread
A13: S-010 | B13: Global | C13: Access layer | D13: Finsight (ABS deal browser) | E13: Finsight | F13: ABS all | G13: Deal discovery | H13: Deal-level | I13: Live | J13: - | K13: Free browse; clean CSVs paid | L13: Manual | M13: - | N13: - | O13: P3 | P13: Not started | Q13: - | R13: Paid tier for CSV exports | S13: finsight.com | T13: Use raw EDGAR XML for free loan-level
A14: S-011 | B14: Global | C14: Loan-level micro | D14: European DataWarehouse (EDW) | E14: EDW | F14: EU retail ABS | G14: PD/LGD; ESMA templates as schema | H14: Loan-level | I14: Monthly | J14: 2012+, 100M+ loans | K14: Paid / researcher request | L14: - | M14: - | N14: - | O14: P3 | P14: Not started | Q14: ref.schemas (templates) | R14: Bulk is paid | S14: eurodw.eu | T14: ESMA templates free = canonical EU loan-record schema
... A59: S-056 | B59: Global | C59: Regulatory filings | D59: FFIEC Call Reports (RC-C/RC-N/RI-B) | E59: FFIEC | F59: All US banks | G59: Bank-level PD + recovery proxies | H59: Bank-quarter | I59: Quarterly | J59: 1984+ | K59: Open | L59: Bulk download | M59: Selective | N59: Quarterly | O59: P2 | P59: Not started | Q59: agg.bank_panel | R59: Public | S59: cdr.ffiec.gov | T59: Charge-offs AND recoveries
A60: S-057 | B60: Global | C60: Regulatory filings | D60: NCUA credit union call reports | E60: NCUA | F60: Credit unions | G60: Delinquency/charge-off by loan type | H60: CU-quarter ZIPs | I60: Quarterly | J60: 1994+ | K60: Open | L60: Bulk ZIPs | M60: Selective | N60: Quarterly | O60: P3 | P60: Not started | Q60: agg.bank_panel | R60: Public | S60: ncua.gov
A61: S-058 | B61: Global | C61: Regulatory filings | D61: FDIC BankFind Suite API + QBP | E61: FDIC | F61: US banks | G61: Loss cross-sections | H61: Bank-quarter | I61: Quarterly | J61: 1992+ | K61: Open | L61: REST API | M61: Selective | N61: Quarterly | O61: P2 | P61: Not started | Q61: agg.bank_panel | R61: Public | S61: banks.data.fdic.gov | T61: No-auth API
A62: S-059 | B62: Global | C62: Aggregate benchmark | D62: Philadelphia Fed large-bank card & mortgage data (Y-14M) | E62: Philadelphia Fed | F62: Cards, Mortgage | G62: EAD/utilization/payment-rate anchors by score band | H62: Score-band series | I62: Quarterly | J62: 2012+ | K62: Open | L62: CSV + FRED | M62: Full history | N62: Quarterly | O62: P1 | P62: Not started | Q62: agg.anchor_series | R62: Public | S62: philadelphiafed.org | T62: Best public EAD/CCF anchor; 67 new series Jul 2025
A63: S-060 | B63: Global | C63: Aggregate benchmark | D63: CFPB Consumer Credit Trends + CARD Act report | E63: CFPB | F63: Consumer | G63: Origination mix, utilization/CLIP/payment tiers | H63: Score-tier series | I63: Ongoing / biennial | J63: 2005+ (CARD Act 2025 ed.) | K63: Open | L63: CSV/PDF | M63: Full | N63: Biennial | O63: P2 | P63: Not started | Q63: agg.anchor_series | R63: Public domain | S63: consumerfinance.gov | T63: 15% of GP cardholders minimum-paying (2025)
A64: S-061 | B64: Global | C64: Aggregate benchmark | D64: NY Fed Household Debt & Credit (CCP aggregates) | E64: NY Fed | F64: Consumer | G64: Delinquency transition rates by product | H64: Product-quarter | I64: Quarterly | J64: 1999+ | K64: Open | L64: Excel | M64: Full | N64: Quarterly | O64: P2 | P64: Not started | Q64: agg.anchor_series | R64: Public | S64: newyorkfed.org | T64: Micro panel restricted
A65: S-062 | B65: Global | C65: Schema template | D65: FR Y-14Q Schedule H.1 instructions | E65: Federal Reserve | F65: Wholesale schema | G65: Facility-level field definitions | H65: Field spec | I65: - | J65: - | K65: Open | L65: PDF | M65: Once | N65: - | O65: P2 | P65: Not started | Q65: ref.schemas | R65: Public | S65: reginfo.gov | T65: What a bank corporate credit system must hold
A66: S-063 | B66: Global | C66: Aggregate benchmark | D66: OCC Mortgage Metrics + FSA student aid data | E66: OCC / FSA | F66: Mortgage, Student | G66: Servicer performance; cohort default rates | H66: Aggregate | I66: Quarterly | J66: 2008+ | K66: Open | L66: PDF/CSV | M66: Optional | N66: Quarterly | O66: P3 | P66: Not started | Q66: agg.anchor_series | R66: Public | S66: studentaid.gov | T66: FSA: institution-level nonpayment rates since Jul 2025
A67: S-064 | B67: Global | C67: Stress/scenario | D67: BoE Bank Capital Stress Test 2025 + scenario key elements | E67: Bank of England | F67: UK all | G67: Bank-level stressed impairments + macro paths | H67: 7 banks, bank-level | I67: Biennial | J67: 2014+ (2025 pub Dec 2025) | K67: Open | L67: PDF/Excel | M67: 2025 + archive | N67: Biennial | O67: P2 | P67: Not started | Q67: agg.stress_results + scen.macro_paths | R67: Open | S67: bankofengland.co.uk | T67: 2026 expected desk-based aggregate-only
A68: S-065 | B68: Cross-country | C68: Aggregate benchmark | D68: IMF Financial Soundness Indicators | E68: IMF | F68: Country-level | G68: NPL/provisions/capital panel | H68: Country-quarter | I68: Quarterly | J68: 2005+ | K68: Open | L68: SDMX API | M68: Full | N68: Quarterly | O68: P2 | P68: Not started | Q68: agg.country_panel | R68: Open | S68: data.imf.org | T68: India included
A69: S-066 | B69: Cross-country | C69: Aggregate benchmark | D69: OECD Financing SMEs Scoreboard 2026 | E69: OECD | F69: SME | G69: SME NPL rates ~50 countries | H69: Country-year | I69: Annual | J69: 2007-2024 | K69: Open | L69: Excel | M69: Full | N69: Annual | O69: P2 | P69: Not started | Q69: agg.country_panel | R69: Open | S69: oecd.org | T69: SME benchmark corridor
A70: S-067 | B70: Cross-country | C70: Aggregate benchmark | D70: BIS credit to NFS, credit gaps, DSRs | E70: BIS | F70: Macro | G70: Early-warning features | H70: Country-quarter | I70: Quarterly | J70: 1960s+ | K70: Open | L70: Bulk CSV/SDMX | M70: Full | N70: Quarterly | O70: P2 | P70: Not started | Q70: agg.country_panel | R70: Open | S70: data.bis.org | T70: India included
A71: S-068 | B71: Cross-country | C71: Aggregate benchmark | D71: World Bank GFDD | E71: World Bank | F71: Macro-financial structure | G71: Structure indicators | H71: Country-year | I71: Static (to 2021) | J71: 1960-2021 | K71: Open | L71: Excel | M71: Once | N71: - | O71: P3 | P71: Not started | Q71: agg.country_panel | R71: CC BY | S71: worldbank.org | T71: Stale - structure only
A72: S-069 | B72: Cross-country | C72: Aggregate benchmark | D72: Doing Business Resolving Insolvency archive + B-READY | E72: World Bank | F72: Corporate LGD | G72: Recovery cents-on-dollar by country | H72: Country-year | I72: Static (archive) | J72: 2004-2019 (B-READY 2025) | K72: Open | L72: Archive download | M72: Once | N72: - | O72: P2 | P72: Not started | Q72: agg.country_panel | R72: Open | S72: archive.doingbusiness.org | T72: Cross-country LGD prior + regime scores
... A112: S-109 | B112: India | C112: Ecosystem stats | D112: Sahamati Account Aggregator statistics | E112: Sahamati | F112: Underwriting rail | G112: AA adoption trajectory | H112: Ecosystem counts | I112: Ongoing | J112: 2021+ | K112: Open | L112: Web | M112: - | N112: Quarterly | O112: P3 | P112: Not started | Q112: docs library | R112: Open | S112: sahamati.org.in | T112: ~24 cr consents; future cash-flow underwriting rail

Sheet Dashboard
A1: CREDIT RISK DATA PROGRAMME — DASHBOARD
A2: All figures computed live from the tracker sheets. Update Status columns there; this page follows.
A4: HEADLINE | E4: SOURCES: STATUS x PRIORITY
A5: Data sources tracked | C5: =COUNTA('1_Sources'!$A$4:$A$112) -> 109 | E5: Priority | F5: Not started | G5: In progress | H5: Fetched | I5: Cleaned | J5: Loaded | K5: Validated | L5: Done | M5: Blocked | N5: N/A | O5: Total
A6: Sources done (Loaded/Validated/Done) | C6: =COUNTIF('1_Sources'!$P$4:$P$112,"Loaded")+COUNTIF('1_Sources'!$P$4:$P$112,"Validated")+COUNTIF('1_Sources'!$P$4:$P$112,"Done") -> 0 | E6: P1 | F6: =COUNTIFS('1_Sources'!$O$4:$O$112,"P1",'1_Sources'!$P$4:$P$112,"Not started") -> 38 | G6: =COUNTIFS('1_Sources'!$O$4:$O$112,"P1",'1_Sources'!$P$4:$P$112,"In progress") -> 0 | H6: =COUNTIFS('1_Sources'!$O$4:$O$112,"P1",'1_Sources'!$P$4:$P$112,"Fetched") -> 0 | I6: =COUNTIFS('1_Sources'!$O$4:$O$112,"P1",'1_Sources'!$P$4:$P$112,"Cleaned") -> 0 | J6: =COUNTIFS('1_Sources'!$O$4:$O$112,"P1",'1_Sources'!$P$4:$P$112,"Loaded") -> 0 | K6: =COUNTIFS('1_Sources'!$O$4:$O$112,"P1",'1_Sources'!$P$4:$P$112,"Validated") -> 0 | L6: =COUNTIFS('1_Sources'!$O$4:$O$112,"P1",'1_Sources'!$P$4:$P$112,"Done") -> 0 | M6: =COUNTIFS('1_Sources'!$O$4:$O$112,"P1",'1_Sources'!$P$4:$P$112,"Blocked") -> 0 | N6: =COUNTIFS('1_Sources'!$O$4:$O$112,"P1",'1_Sources'!$P$4:$P$112,"N/A") -> 0 | O6: =COUNTIF('1_Sources'!$O$4:$O$112,"P1") -> 38
A7: Sources in flight (In progress/Fetched/Cleaned) | C7: =COUNTIF('1_Sources'!$P$4:$P$112,"In progress")+COUNTIF('1_Sources'!$P$4:$P$112,"Fetched")+COUNTIF('1_Sources'!$P$4:$P$112,"Cleaned") -> 0 | E7: P2 | F7: =COUNTIFS('1_Sources'!$O$4:$O$112,"P2",'1_Sources'!$P$4:$P$112,"Not started") -> 37 | G7: =COUNTIFS('1_Sources'!$O$4:$O$112,"P2",'1_Sources'!$P$4:$P$112,"In progress") -> 0 | H7: =COUNTIFS('1_Sources'!$O$4:$O$112,"P2",'1_Sources'!$P$4:$P$112,"Fetched") -> 0 | I7: =COUNTIFS('1_Sources'!$O$4:$O$112,"P2",'1_Sources'!$P$4:$P$112,"Cleaned") -> 0 | J7: =COUNTIFS('1_Sources'!$O$4:$O$112,"P2",'1_Sources'!$P$4:$P$112,"Loaded") -> 0 | K7: =COUNTIFS('1_Sources'!$O$4:$O$112,"P2",'1_Sources'!$P$4:$P$112,"Validated") -> 0 | L7: =COUNTIFS('1_Sources'!$O$4:$O$112,"P2",'1_Sources'!$P$4:$P$112,"Done") -> 0 | M7: =COUNTIFS('1_Sources'!$O$4:$O$112,"P2",'1_Sources'!$P$4:$P$112,"Blocked") -> 0 | N7: =COUNTIFS('1_Sources'!$O$4:$O$112,"P2",'1_Sources'!$P$4:$P$112,"N/A") -> 0 | O7: =COUNTIF('1_Sources'!$O$4:$O$112,"P2") -> 37
A8: Source completion % | C8: =IFERROR((COUNTIF('1_Sources'!$P$4:$P$112,"Loaded")+COUNTIF('1_Sources'!$P$4:$P$112,"Validated")+COUNTIF('1_Sources'!$P$4:$P$112,"Done"))/MAX(1,COUNTA('1_Sources'!$A$4:$A$112)-COUNTIF('1_Sources'!$P$4:$P$112,"N/A")),0) -> 0 | E8: P3 | F8: =COUNTIFS('1_Sources'!$O$4:$O$112,"P3",'1_Sources'!$P$4:$P$112,"Not started") -> 34 | G8: =COUNTIFS('1_Sources'!$O$4:$O$112,"P3",'1_Sources'!$P$4:$P$112,"In progress") -> 0 | H8: =COUNTIFS('1_Sources'!$O$4:$O$112,"P3",'1_Sources'!$P$4:$P$112,"Fetched") -> 0 | I8: =COUNTIFS('1_Sources'!$O$4:$O$112,"P3",'1_Sources'!$P$4:$P$112,"Cleaned") -> 0 | J8: =COUNTIFS('1_Sources'!$O$4:$O$112,"P3",'1_Sources'!$P$4:$P$112,"Loaded") -> 0 | K8: =COUNTIFS('1_Sources'!$O$4:$O$112,"P3",'1_Sources'!$P$4:$P$112,"Validated") -> 0 | L8: =COUNTIFS('1_Sources'!$O$4:$O$112,"P3",'1_Sources'!$P$4:$P$112,"Done") -> 0 | M8: =COUNTIFS('1_Sources'!$O$4:$O$112,"P3",'1_Sources'!$P$4:$P$112,"Blocked") -> 0 | N8: =COUNTIFS('1_Sources'!$O$4:$O$112,"P3",'1_Sources'!$P$4:$P$112,"N/A") -> 0 | O8: =COUNTIF('1_Sources'!$O$4:$O$112,"P3") -> 34
A9: Pipelines done | C9: =COUNTIF('4_Pipelines'!$K$4:$K$35,"Done")+COUNTIF('4_Pipelines'!$K$4:$K$35,"Validated")+COUNTIF('4_Pipelines'!$K$4:$K$35,"Loaded") -> 0
A10: Assembly projects done | C10: =COUNTIF('2_Assembly'!$L$4:$L$10,"Done") -> 0 | E10: SOURCES BY REGION | F10: Total | G10: Done
A11: Prototypes done | C11: =COUNTIF('3_Prototypes'!$K$4:$K$15,"Done") -> 0 | E11: Global | F11: =COUNTIF('1_Sources'!$B$4:$B$112,"Global") -> 64 | G11: =COUNTIFS('1_Sources'!$B$4:$B$112,"Global",'1_Sources'!$P$4:$P$112,"Loaded")+COUNTIFS('1_Sources'!$B$4:$B$112,"Global",'1_Sources'!$P$4:$P$112,"Validated")+COUNTIFS('1_Sources'!$B$4:$B$112,"Global",'1_Sources'!$P$4:$P$112,"Done") -> 0
A12: Watchlist open items | C12: =COUNTIF('8_Watchlist'!$G$4:$G$21,"Not started")+COUNTIF('8_Watchlist'!$G$4:$G$21,"In progress") -> 18 | E12: India | F12: =COUNTIF('1_Sources'!$B$4:$B$112,"India") -> 34 | G12: =COUNTIFS('1_Sources'!$B$4:$B$112,"India",'1_Sources'!$P$4:$P$112,"Loaded")+COUNTIFS('1_Sources'!$B$4:$B$112,"India",'1_Sources'!$P$4:$P$112,"Validated")+COUNTIFS('1_Sources'!$B$4:$B$112,"India",'1_Sources'!$P$4:$P$112,"Done") -> 0
E13: EM | F13: =COUNTIF('1_Sources'!$B$4:$B$112,"EM") -> 2 | G13: =COUNTIFS('1_Sources'!$B$4:$B$112,"EM",'1_Sources'!$P$4:$P$112,"Loaded")+COUNTIFS('1_Sources'!$B$4:$B$112,"EM",'1_Sources'!$P$4:$P$112,"Validated")+COUNTIFS('1_Sources'!$B$4:$B$112,"EM",'1_Sources'!$P$4:$P$112,"Done") -> 0
E14: Cross-country | F14: =COUNTIF('1_Sources'!$B$4:$B$112,"Cross-country") -> 9 | G14: =COUNTIFS('1_Sources'!$B$4:$B$112,"Cross-country",'1_Sources'!$P$4:$P$112,"Loaded")+COUNTIFS('1_Sources'!$B$4:$B$112,"Cross-country",'1_Sources'!$P$4:$P$112,"Validated")+COUNTIFS('1_Sources'!$B$4:$B$112,"Cross-country",'1_Sources'!$P$4:$P$112,"Done") -> 0
A16: WORKSTREAM PROGRESS
A17: Workstream | B17: Total | C17: Not started | D17: In flight | E17: Done
A18: 1. Sources | B18: =COUNTA('1_Sources'!$P$4:$P$112) -> 109 | C18: =COUNTIF('1_Sources'!$P$4:$P$112,"Not started") -> 109 | D18: =COUNTIF('1_Sources'!$P$4:$P$112,"In progress")+COUNTIF('1_Sources'!$P$4:$P$112,"Fetched")+COUNTIF('1_Sources'!$P$4:$P$112,"Cleaned") -> 0 | E18: =COUNTIF('1_Sources'!$P$4:$P$112,"Done")+COUNTIF('1_Sources'!$P$4:$P$112,"Validated")+COUNTIF('1_Sources'!$P$4:$P$112,"Loaded") -> 0
A19: 2. Assembly projects | B19: =COUNTA('2_Assembly'!$L$4:$L$10) -> 7 | C19: =COUNTIF('2_Assembly'!$L$4:$L$10,"Not started") -> 7 | D19: =COUNTIF('2_Assembly'!$L$4:$L$10,"In progress")+COUNTIF('2_Assembly'!$L$4:$L$10,"Fetched")+COUNTIF('2_Assembly'!$L$4:$L$10,"Cleaned") -> 0 | E19: =COUNTIF('2_Assembly'!$L$4:$L$10,"Done")+COUNTIF('2_Assembly'!$L$4:$L$10,"Validated")+COUNTIF('2_Assembly'!$L$4:$L$10,"Loaded") -> 0
A20: 3. Prototypes | B20: =COUNTA('3_Prototypes'!$K$4:$K$15) -> 12 | C20: =COUNTIF('3_Prototypes'!$K$4:$K$15,"Not started") -> 12 | D20: =COUNTIF('3_Prototypes'!$K$4:$K$15,"In progress")+COUNTIF('3_Prototypes'!$K$4:$K$15,"Fetched")+COUNTIF('3_Prototypes'!$K$4:$K$15,"Cleaned") -> 0 | E20: =COUNTIF('3_Prototypes'!$K$4:$K$15,"Done")+COUNTIF('3_Prototypes'!$K$4:$K$15,"Validated")+COUNTIF('3_Prototypes'!$K$4:$K$15,"Loaded") -> 0
A21: 4. Pipelines | B21: =COUNTA('4_Pipelines'!$K$4:$K$35) -> 32 | C21: =COUNTIF('4_Pipelines'!$K$4:$K$35,"Not started") -> 32 | D21: =COUNTIF('4_Pipelines'!$K$4:$K$35,"In progress")+COUNTIF('4_Pipelines'!$K$4:$K$35,"Fetched")+COUNTIF('4_Pipelines'!$K$4:$K$35,"Cleaned") -> 0 | E21: =COUNTIF('4_Pipelines'!$K$4:$K$35,"Done")+COUNTIF('4_Pipelines'!$K$4:$K$35,"Validated")+COUNTIF('4_Pipelines'!$K$4:$K$35,"Loaded") -> 0
A22: 5. DB tables | B22: =COUNTA('5_DB_Schema'!$H$4:$H$19) -> 16 | C22: =COUNTIF('5_DB_Schema'!$H$4:$H$19,"Not started") -> 16 | D22: =COUNTIF('5_DB_Schema'!$H$4:$H$19,"In progress")+COUNTIF('5_DB_Schema'!$H$4:$H$19,"Fetched")+COUNTIF('5_DB_Schema'!$H$4:$H$19,"Cleaned") -> 0 | E22: =COUNTIF('5_DB_Schema'!$H$4:$H$19,"Done")+COUNTIF('5_DB_Schema'!$H$4:$H$19,"Validated")+COUNTIF('5_DB_Schema'!$H$4:$H$19,"Loaded") -> 0
A23: 8. Watchlist | B23: =COUNTA('8_Watchlist'!$G$4:$G$21) -> 18 | C23: =COUNTIF('8_Watchlist'!$G$4:$G$21,"Not started") -> 18 | D23: =COUNTIF('8_Watchlist'!$G$4:$G$21,"In progress")+COUNTIF('8_Watchlist'!$G$4:$G$21,"Fetched")+COUNTIF('8_Watchlist'!$G$4:$G$21,"Cleaned") -> 0 | E23: =COUNTIF('8_Watchlist'!$G$4:$G$21,"Done")+COUNTIF('8_Watchlist'!$G$4:$G$21,"Validated")+COUNTIF('8_Watchlist'!$G$4:$G$21,"Loaded") -> 0

Sheet 2_Assembly
A1: 2. ASSEMBLY PROJECTS — the differentiated datasets to build
A2: Five flagship datasets nobody has assembled + the anchor warehouse + synthesis. Research phase is complete; build phase starts now.
A3: ID | B3: Project | C3: Description | D3: Doc ref | E3: Research status | F3: Layer-1 inputs | G3: Layer-2 anchors | H3: Key steps | I3: Deliverable | J3: Dependencies | K3: Priority | L3: Build status | M3: % complete | N3: Notes
A4: AP-1 | B4: IBBI case-level corporate LGD dataset | C4: Extract Table 5 (CIRPs yielding resolution) + liquidation tables from every IBBI quarterly newsletter into a company-named workout-LGD dataset (~1,400 resolutions) with claims, liquidation/fair values, realisation and durations. | D4: §4.2 | E4: Done (verified Jul-26) | F4: IBBI quarterly newsletter PDFs (S-079) | G4: IBBI headline ratios; T&P recovery-by-channel; GEMs | H4: 1) Download all newsletters 2) PDF table extraction (pdfplumber/camelot) 3) Normalize entity names 4) QA vs published cumulative ratios 5) Load micro.default_events + micro.recovery_cashflows 6) Derive LGD distribution + time-to-resolution curves | I4: India corporate workout-LGD dataset + recovery-timing curves | J4: PL-20 | K4: P1 | L4: Not started | M4: 0 | N4: Flagship. Realisation ratios drift by quarter — record cutoff per case.
A5: AP-2 | B5: India corporate default-event & rating-migration corpus | C5: Assemble issuer-level default labels + full rating histories from CRA Annexure V/VI files, daily NSE/BSE rating feeds, Reg 57 intimations and CIC defaulter registries; India's 17g-7 equivalent. | D5: §4.2 | E5: Done (verified Jul-26) | F5: Annexure V/VI Excels (7 CRAs) (S-084); exchange feeds (S-083); CIC registries (S-081); indiabondinfo (S-082) | G5: CRA default studies (CDRs, matrices) (S-085); NeSL (S-080) | H5: 1) Collect Annexure V/VI archives 2) Normalize scales/issuer names across CRAs 3) Ingest daily exchange rating feeds from Aug-25 4) Scrape Reg 57 announcements 5) Entity-resolve vs CIC registries 6) Build migration matrices + default-event table 7) Validate vs published CDRs | I5: Issuer-level Indian rating-migration panel + default-event history | J5: PL-22, PL-23, PL-24 | K5: P1 | L5: Not started | M5: 0 | N5: Studies do NOT name defaulters — Annexure VI does.
A6: AP-3 | B6: India NBFC ECL panel | C6: Extract stage-wise gross exposure, ECL allowance, coverage, PD/LGD assumptions and scenario weights from ~50 NBFC annual reports x FY19-FY26. | D6: §4.5 | E6: Done (3 NBFCs verified) | F6: NBFC annual reports (S-101); Chola ECL methodology doc | G6: ECB/EBA stage benchmarks; RBI floors (0.40%/5%) | H6: 1) Fix NBFC universe (~50) 2) Collect ARs FY19-FY26 3) LLM-assisted note extraction + human QA 4) Normalize product taxonomies 5) Panelize stage coverage by product-year 6) Benchmark vs EU stage data | I6: Product-level India ECL panel (stage EAD, coverage, PD/LGD disclosures) | J6: PL-25 | K6: P1 | L6: Not started | M6: 0 | N6: Value spikes toward Apr-2027 bank ECL deadline.
A7: AP-4 | B7: EU cross-bank IRB parameter panel (P3DH) | C7: Bulk-download P3DH machine-readable Pillar 3 (CR6/CR10) and panelize EAD-weighted PD/LGD/RW/EL by bank x exposure class x PD band x ref date. | D7: §3.1 | E7: Done (P3DH live 26-Jan-26) | F7: EBA P3DH bulk CSVs (S-045) | G7: EBA benchmarking dispersion report (S-048); transparency exercise (S-047) | H7: 1) Bulk download all ref dates 2) Parse DPM/XBRL-CSV 3) Build agg.irb_parameters 4) Dispersion analytics 5) Refresh semiannually | I7: Cross-bank IRB PD/LGD benchmark panel + dispersion views | J7: PL-12 | K7: P1 | L7: Not started | M7: 0 | N7: Global benchmark product; replaces PDF scraping.
A8: AP-5 | B8: India district-risk panel | C8: Join SLBC district NPA tables with BSR-1 district credit (occupation x rate bucket) and state microfinance PAR into a district-level risk surface. | D8: §4.4 | E8: Done (KL/PB/WB verified) | F8: SLBC minutes (S-100); BSR-1 (S-077) | G8: MFIN/CRIF state-district PAR (S-095/094); NABARD SHG (S-099) | H8: 1) Pilot 3 states' SLBC PDFs 2) District-name normalization (LGD codes) 3) Merge BSR-1 credit 4) Layer microfinance PAR 5) Build agg.india_geo_panel 6) Expand states | I8: District-level India credit-risk surface (concentration, geo-stress) | J8: PL-28, PL-29 | K8: P2 | L8: Not started | M8: 0 | N8: Unique geographic asset; useful for climate overlays later.
A9: AP-6 | B9: Global anchor warehouse | C9: Digitize every benchmark table (agency studies, GEMs, GCD, BdI, ICC, Philly Fed, Fed charge-offs, EBA/ECB stage data, bureau PDFs) into one long-format anchor store with source/as-of metadata. | D9: §3, §7.1 | E9: Done (sources verified) | F9: — | G9: All Layer-2 sources (S-031..S-078, India S-075..S-107) | H9: 1) Define agg.anchor_series long schema (source, segment, metric, period, value, asof, url) 2) Prioritized digitization backlog 3) Automated pulls where API exists 4) QA vs doc's key numbers (6_Anchors) 5) Refresh calendar | I9: Queryable calibration-anchor database powering all prototypes | J9: PL-10..PL-19, PL-26, PL-27 | K9: P1 | L9: Not started | M9: 0 | N9: The backbone — do early; everything validates against it.
A10: AP-7 | B10: India synthetic loan books (retail/MSME/corporate) | C10: Constrained synthetic generation: fit dependence on Layer-1 micro (Home Credit/LTFS/Freddie), reweight to reproduce India Layer-2 anchors (bureau PAR, FSR, NBFC ECL panel). | D10: §7.1 | E10: Done (method set) | F10: Home Credit (S-017/018); LTFS (S-103); Freddie (S-001); Bondora (S-014) | G10: CMI/MSME Pulse/CRIF/MFIN (S-092..095); FSR (S-075); AP-3 panel | H10: 1) Build facility schema (AnaCredit-shaped) 2) Fit copulas/CTGAN on Layer-1 3) Calibrate marginals to anchors 4) Prove reproduction of targets 5) Package as teaching/prototype datasets | I10: Synthetic India books that provably reproduce published aggregates | J10: AP-1, AP-3, AP-6 | K10: P1 | L10: Not started | M10: 0 | N10: SDV/CTGAN + reweighting; document constraints per book.

Sheet 3_Prototypes
A1: 3. MODEL PROTOTYPES — starter stacks
A2: One row per planned prototype, mapped to its Layer-1/Layer-2 data and regulatory hook (doc §7.2).
A3: ID | B3: Prototype | C3: Portfolio | D3: Doc ref | E3: Layer-1 micro data | F3: Layer-2 anchors | G3: Regulatory hook | H3: Deliverable | I3: Depends on | J3: Priority | K3: Status | L3: Notes
A4: M-01 | B4: Mortgage PD + LGD + prepayment pipeline | C4: Mortgage | D4: §7.2 | E4: Freddie SFLLD (loss columns) (S-001) | F4: DFAST loss rates; EBA IRB CSV; FHFA HPI paths | G4: IFRS9/ECL lifetime, Basel IRB | H4: End-to-end PD/LGD/prepay models + ECL engine demo | I4: PL-01 | J4: P1 | K4: Not started | L4: Validates the whole architecture first
A5: M-02 | B5: Auto PD + LGD + recovery timing | C5: Auto | D5: §7.2 | E5: ABS-EE EX-102 (S-007); LTFS (S-103) for India scorecard | F5: Manheim; CRIF auto/2W PAR; PTC pool rationales | G5: RBI ECL, IFRS9 | H5: Auto book models incl. workout-recovery timing | I5: PL-03, PL-07 | J5: P1 | K5: Not started | L5: Both geographies have micro data here
A6: M-03 | B6: Behavioural card + EAD/CCF | C6: Cards | D6: §7.2 | E6: Amex panel (S-019); master trust 10-Ds (S-009) | F6: Philly Fed utilization by score band; CFPB CARD Act tiers | G6: Basel CCF, IFRS9 EAD | H6: Behavioural PD + utilization/CCF model with anchored calibration | I6: PL-04, PL-07, PL-10 | J6: P1 | K6: Not started | L6: EAD story is anchor-based by design
A7: M-04 | B7: Application scorecard + stability monitoring | C7: Personal (EM) | D7: §7.2 | E7: Home Credit 2018 + 2024 (S-017/018); LendingClub rejects (S-013) | F7: NY Fed transitions; CIBIL CMI risk tiers | G7: RBI draft MRM guidance | H7: Scorecard + reject inference + OOT stability/PSI monitoring kit | I7: PL-07 | J7: P1 | K7: Not started | L7: 2024 set = ready-made monitoring testbed
A8: M-05 | B8: Unsecured consumer workout LGD + cure | C8: Personal | D8: §7.2 | E8: Bondora recovery cashflows (S-014) | F8: GCD unsecured LGD ~27%; P2P India disclosures | G8: IFRS9 LGD, RBI ECL | H8: Workout-LGD, cure-rate and recovery-timing models | I8: PL-06 | J8: P1 | K8: Not started | L8: Only free consumer recovery-cashflow data
A9: M-06 | B9: SME/MSME PD + LGD | C9: SME/MSME | D9: §7.2 | E9: SBA 7(a) charge-offs (S-012) | F9: MSME Pulse by ticket/CMR; CGTMSE claims; OECD SME NPLs; EBA SME IRB | G9: RBI ECL (MSME book) | H9: SME scorecard + LGD distribution + India MSME calibration | I9: PL-05, PL-26 | J9: P1 | K9: Not started
A10: M-07 | B10: Corporate PD + rating migration | C10: Corporate | D10: §7.2 | E10: ratingshistory + EDGAR XBRL + FJC (S-028/029/030); India corpus (AP-2) | F10: S&P/Moody's studies; CRISIL/ICRA matrices; NUS-CRI; NeSL | G10: Basel IRB, ICAAP | H10: Transition matrices, PD term structures, Altman/Merton scorecards | I10: AP-2, PL-16 | J10: P1 | K10: Not started
A11: M-08 | B11: Corporate LGD (India-led) | C11: Corporate | D11: §7.2 | E11: IBBI Table 5 case data (AP-1) | F11: GEMs 72.9%; GCD seniority; BdI 41%; T&P channel table | G11: RBI ECL LGD, IFRS9 | H11: India corporate LGD model + channel-conditional structure | I11: AP-1 | J11: P1 | K11: Not started | L11: India's unique strength
A12: M-09 | B12: Microfinance stress & SICR demo | C12: Microfinance | D12: §7.2 | E12: (synthesize) | F12: MFIN+Sa-Dhan+CRIF+Equifax full-cycle state panel; MIX global | G12: RBI ECL staging/SICR | H12: State-level stress model + SICR trigger demonstration on real cycle | I12: PL-26, AP-6 | J12: P2 | K12: Not started | L12: FY24-26 cycle = rare gift
A13: M-10 | B13: IFRS9 / RBI ECL engine | C13: All-portfolio | D13: §7.2 | E13: Any Layer-1 for PD term structures | F13: NBFC ECL panel (AP-3); ECB stage stats; EBA IFRS9 reports; RBI floors | G13: RBI ECL Directions 2026 | H13: Full 3-stage ECL engine with floors, SICR, scenario weights | I13: AP-3, AP-6, M-01 | J13: P1 | K13: Not started | L13: The commercial centerpiece for Apr-2027
A14: M-11 | B14: Stress testing / ICAAP suite | C14: All-portfolio | D14: §7.2 | E14: — | F14: Fed/BoE/RBI FSR scenarios; Fed charge-off satellites; Laeven-Valencia tails; NGFS climate | G14: ICAAP, RBI FSR methodology | H14: Macro-satellite models + scenario engine + climate overlay | I14: PL-17, AP-6 | J14: P1 | K14: Not started | L14: Validate severe vs RBI adverse range
A15: M-12 | B15: Wholesale IRB benchmarking tool | C15: Wholesale | D15: §7.2 | E15: — | F15: P3DH CR6 panel (AP-4); EBA benchmarking dispersion | G15: Basel IRB validation | H15: Benchmark-your-parameters tool vs EU bank distribution | I15: AP-4 | J15: P2 | K15: Not started

Sheet 4_Pipelines
A1: 4. PIPELINES — fetch/parse/load engineering tasks
A2: One row per data-engineering task. Effort: S <1 day, M 1-3 days, L 1-2 weeks (order of magnitude).
A3: ID | B3: Task | C3: Feeds from | D3: Method | E3: Tooling & anti-bot notes | F3: Output table | G3: Backfill range | H3: Refresh schedule | I3: Effort | J3: Priority | K3: Status | L3: Notes
A4: PL-01 | B4: Freddie SFLLD downloader + loader | C4: S-001 | D4: Bulk ZIP -> parquet | E4: Registration cookie; 100GB+ full history — start with sample file + selected vintages | F4: micro.facility_master/performance/recovery | G4: 1999-2025 | H4: Quarterly | I4: L | J4: P1 | K4: Not started | L4: Reference pipeline for everything
A5: PL-02 | B5: Fannie CAS enhanced loader | C5: S-002 | D5: Bulk download | E5: Similar to PL-01 | F5: micro.* | G5: 2000-2025 | H5: Quarterly | I5: M | J5: P2 | K5: Not started
A6: PL-03 | B6: ABS-EE EX-102 XML parser (auto shelves) | C6: S-007 | D6: EDGAR index -> 10-D exhibits -> XML | E6: Respect SEC rate limits (10 req/s, declared UA); schema per Reg AB II | F6: micro.facility_master/recovery | G6: 2016+ | H6: Monthly | I6: L | J6: P1 | K6: Not started | L6: Start: 2-3 shelves (Ford, Santander)
A7: PL-04 | B7: Card master-trust 10-D parser | C7: S-009 | D7: EDGAR scrape + table parse | E7: Exhibit formats vary by trust; regex/table heuristics per trust | F7: agg.card_trust_series | G7: ~2000+ | H7: Monthly | I7: M | J7: P1 | K7: Not started | L7: Chase + Citi first
A8: PL-05 | B8: SBA 7(a)/504 loader | C8: S-012 | D8: CSV download | E8: Straightforward | F8: micro.facility_master | G8: 1991+ | H8: Quarterly | I8: S | J8: P1 | K8: Not started
A9: PL-06 | B9: Bondora/Go&Grow ingester | C9: S-014 | D9: XLSX + snapshot archives | E9: Schema drift across vintages; API is dead | F9: micro.recovery_cashflows | G9: 2009+ | H9: Quarterly | I9: S | J9: P1 | K9: Not started
A10: PL-07 | B10: Kaggle fetcher (Amex, HC18, HC24, LC, LTFS, GMSC) | C10: S-013/017/018/019/103 | D10: kaggle CLI | E10: Accept competition rules in browser first; store raw + license note | F10: micro.* various | G10: Static | H10: None | I10: S | J10: P1 | K10: Not started
A11: PL-08 | B11: Berka MariaDB pull | C11: S-020 | D11: SQL (guest/ctu-relational) | E11: Public guest credentials | F11: micro.transactions | G11: Static | H11: None | I11: S | J11: P2 | K11: Not started
A12: PL-09 | B12: MIX Market loader | C12: S-025 | D12: Excel/ZIP | E12: Static archive | F12: agg.mfi_panel | G12: 1999-2019 | H12: None | I12: S | J12: P2 | K12: Not started
A13: PL-10 | B13: FRED + Philly Fed + charge-off pullers | C13: S-054/058 | D13: FRED API + CSV | E13: Free API key | F13: agg.anchor_series | G13: 1985+/2012+ | H13: Quarterly | I13: S | J13: P1 | K13: Not started
A14: PL-11 | B14: FFIEC/NCUA/FDIC pulls | C14: S-055/056/057 | D14: Bulk + REST API | E14: FDIC API is no-auth | F14: agg.bank_panel | G14: Selective | H14: Quarterly | I14: M | J14: P3 | K14: Not started
A15: PL-12 | B15: EBA P3DH bulk downloader | C15: S-045 | D15: Bulk XBRL-CSV | E15: New portal; DPM-aligned schema mapping needed | F15: agg.irb_parameters | G15: Jun-2025+ | H15: Semiannual | I15: M | J15: P1 | K15: Not started | L15: Feeds AP-4
A16: PL-13 | B16: EBA stress/transparency/dashboard ingester | C16: S-046/047/049 | D16: CSV/Excel | E16: Stable formats | F16: agg.stress_results/bank_panel/stage_coverage | G16: 2011+ | H16: Per release | I16: S | J16: P2 | K16: Not started
A17: PL-14 | B17: ECB SUP statistics pull | C17: S-050 | D17: ECB Data Portal API/CSV | E17: SDMX available | F17: agg.stage_coverage | G17: 2015+ | H17: Quarterly | I17: S | J17: P1 | K17: Not started
A18: PL-15 | B18: Banca d'Italia recovery-series digitizer | C18: S-053 (BdI row) | D18: Excel appendix + PDF | E18: Excel appendix published with note | F18: agg.anchor_series | G18: 2006-2024 | H18: Annual | I18: S | J18: P2 | K18: Not started
A19: PL-16 | B19: Benchmark-table digitizer (S&P/Moody's/GEMs/ICC/GCD studies) | C19: S-031/032/034/036/038 | D19: PDF tables -> anchor rows | E19: Manual-assisted; provenance metadata per number | F19: agg.anchor_series | G19: Latest editions | H19: Annual | I19: M | J19: P1 | K19: Not started | L19: Feeds AP-6
A20: PL-17 | B20: Scenario ingesters (Fed/EBA/BoE/RBI FSR/NGFS) | C20: S-053/063/071/075 | D20: CSV/portal downloads | E20: NGFS via IIASA explorer; RBI annex is PDF | F20: scen.macro_paths + scen.climate_paths | G20: Current vintages | H20: Per release | I20: M | J20: P1 | K20: Not started
A21: PL-18 | B21: Brazil BCB SGS/SCR API puller | C21: S-072 | D21: REST API (no key) | E21: python-bcb package | F21: agg.em_comparators | G21: 2012+ | H21: Monthly | I21: S | J21: P3 | K21: Not started | L21: Also = pipeline design study
A22: PL-19 | B22: IMF FSI / BIS / OECD pulls | C22: S-064/065/066 | D22: SDMX / bulk CSV | E22: Standard | F22: agg.country_panel | G22: Full | H22: Quarterly | I22: S | J22: P2 | K22: Not started
A23: PL-20 | B23: IBBI newsletter scraper — Table 5 + liquidation tables | C23: S-079 | D23: PDF table extract (pdfplumber/camelot) | E23: Layout varies by edition; QA extracted totals vs published cumulative ratios | F23: micro.default_events + micro.recovery_cashflows | G23: 2017-2026 all quarters | H23: Quarterly | I23: M | J23: P1 | K23: Not started | L23: FLAGSHIP — feeds AP-1
A24: PL-21 | B24: NeSL statistics digitizer | C24: S-080 | D24: PDF extract | E24: Large PDFs (10MB+) | F24: agg.india_anchor_series | G24: All editions | H24: Quarterly | I24: S | J24: P2 | K24: Not started
A25: PL-22 | B25: Annexure V/VI collector (7 CRAs) | C25: S-084 | D25: Excel download + normalize | E25: Naming/format differs per CRA; issuer-name entity resolution is the hard part | F25: ref.ratings_history + micro.default_events | G25: ~2016+ archives | H25: Half-yearly | I25: L | J25: P1 | K25: Not started | L25: FLAGSHIP — feeds AP-2
A26: PL-23 | B26: NSE/BSE daily rating feed + Reg 57 ingester | C26: S-083 | D26: Feed Excel + announcements endpoints | E26: NSE anti-bot (cookies/UA rotation); BSE simpler; PDFs need parsing for Reg 57 | F26: ref.rating_events_daily | G26: Aug-2025+ (older via announcements) | H26: Daily | I26: M | J26: P1 | K26: Not started
A27: PL-24 | B27: CIC defaulter-registry search protocol | C27: S-081 | D27: Throttled searches (Experian portal) | E27: ToS-sensitive — legal review first; manual-assisted batches; CIBIL 403s bots | F27: ref.entities + micro.default_events | G27: Current stock | H27: Quarterly | I27: M | J27: P3 | K27: Not started | L27: Name-matching to AP-2 corpus
A28: PL-25 | B28: NBFC AR ECL-note extractor (top 50) | C28: S-101 | D28: AR PDF -> stage tables (LLM-assisted + human QA) | E28: Note formats vary; build extraction template per lender | F28: agg.nbfc_ecl_panel | G28: FY19-FY26 | H28: Annual | I28: L | J28: P1 | K28: Not started | L28: FLAGSHIP — feeds AP-3
A29: PL-26 | B29: Bureau/industry PDF digitizer (CMI, MSME Pulse, CRIF, MFIN, Sa-Dhan, Equifax, FACE) | C29: S-092..S-098 | D29: PDF tables -> anchor rows | E29: Backfill archives where hosted; else Wayback | F29: agg.india_anchor_series + agg.india_geo_panel | G29: 3-5y each | H29: Quarterly | I29: M | J29: P1 | K29: Not started
A30: PL-27 | B30: RBI FSR + T&P table extraction | C30: S-075/076 | D30: Manual download + extract | E30: rbidocs is bot/CAPTCHA-gated — manual download step | F30: agg.india_anchor_series + scen.macro_paths | G30: 10y | H30: Semiannual | I30: M | J30: P1 | K30: Not started | L30: Includes SMA + scenario annex
A31: PL-28 | B31: DBIE BSR-1 / sectoral deployment exports | C31: S-077 | D31: Portal CSV/XLSX | E31: Portal quirks post-CIMS migration | F31: agg.india_geo_panel | G31: Full history | H31: Quarterly | I31: S | J31: P1 | K31: Not started | L31: Feeds AP-5
A32: PL-29 | B32: SLBC PDF pilots (KL/PB/WB) | C32: S-100 | D32: PDF extract | E32: Formats vary by state; district-name normalization | F32: agg.india_geo_panel | G32: 2-3y | H32: Quarterly | I32: M | J32: P2 | K32: Not started | L32: Feeds AP-5
A33: PL-30 | B33: PTC rationale scraper (4 CRA sites) | C33: S-102 | D33: Rationale PDF scrape + parse | E33: Volume; dedupe multiple reviews per pool | F33: agg.pool_series_india | G33: 3y pilot | H33: Monthly | I33: M | J33: P2 | K33: Not started
A34: PL-31 | B34: CGTMSE/MUDRA/NHB/NAFSCOB digitizers | C34: S-086/087/088/089/091 | D34: PDF/portal extract | E34: Annual cadence, low volume | F34: agg.india_anchor_series + idx.collateral_indices | G34: 5-10y | H34: Annual | I34: M | J34: P3 | K34: Not started
A35: PL-32 | B35: P2P factsheet scraper | C35: S-104 | D35: Monthly PDF/page scrape | E35: Formats vary by platform | F35: agg.india_anchor_series | G35: 2-3y | H35: Monthly | I35: S | J35: P3 | K35: Not started

Sheet 5_DB_Schema
A1: 5. DATABASE SCHEMA — where everything lands
A2: Target model: AnaCredit-shaped micro layer + openNPL-shaped default/recovery layer + long-format aggregate anchors. Doc §6.
A3: ID | B3: Layer | C3: Schema.Table | D3: Grain | E3: Template basis | F3: Key fields (illustrative) | G3: Fed by (source IDs) | H3: Status | I3: Notes
A4: T-01 | B4: Reference | C4: ref.entities | D4: One row per obligor/entity | E4: AnaCredit + RIAD | F4: entity_id, name(s), LEI/CIN/PAN, sector, geography, size class | G4: S-081, S-084, S-029, S-105 | H4: Not started | I4: Entity resolution backbone (India + global)
A5: T-02 | B5: Reference | C5: ref.schemas | D5: Documentation | E5: AnaCredit, EBA NPL, Y-14 H.1, ESMA, CR6 | F5: Field dictionaries + mappings | G5: S-011, S-052, S-061 | H5: Not started | I5: Adopt, don't invent
A6: T-03 | B6: Micro | C6: micro.facility_master | D6: One row per facility at origination | E6: AnaCredit instrument | F6: facility_id, entity_id, product, orig_date, amount, rate, LTV, term, channel | G6: S-001/002/007/012/014/103 | H6: Not started
A7: T-04 | B7: Micro | C7: micro.performance_monthly | D7: Facility-month | E7: AnaCredit + servicer templates | F7: facility_id, month, balance, dpd, status, payment, utilization | G7: S-001/002/007/014/019 | H7: Not started | I7: The panel layer
A8: T-05 | B8: Micro | C8: micro.applications(_india) | D8: One row per application | E8: Home Credit / HMDA shape | F8: app_id, applicant features, bureau features, decision, outcome | G8: S-006/013/017/018/103 | H8: Not started | I8: Includes rejects where available
A9: T-06 | B9: Micro | C9: micro.default_events | D9: One row per default event | E9: EBA NPL / openNPL | F9: entity/facility_id, event_date, type (90dpd/insolvency/suit/rating-D), source | G9: AP-1, AP-2, S-030 | H9: Not started | I9: Multi-source event table
A10: T-07 | B10: Micro | C10: micro.recovery_cashflows | D10: Event x cashflow | E10: EBA NPL templates | F10: event_id, date, amount, type (principal/interest/cost), channel, collateral | G10: S-001/007/014, AP-1 | H10: Not started | I10: The LGD engine input
A11: T-08 | B11: Micro | C11: micro.behavioural_panel / micro.transactions | D11: Customer-month / transaction | E11: — | F11: customer_id, period, spend/payment/balance blocks | G11: S-019/020/024 | H11: Not started
A12: T-09 | B12: Aggregate | C12: agg.anchor_series | D12: Source x segment x metric x period | E12: Long format | F12: source_id, segment_json, metric, period, value, asof, url | G12: AP-6 (many) | H12: Not started | I12: Backbone of Layer 2
A13: T-10 | B13: Aggregate | C13: agg.irb_parameters | D13: Bank x exposure class x PD band x ref date | E13: Pillar 3 CR6 | F13: bank, class, pd_band, EAD, wa_PD, wa_LGD, RW, EL | G13: S-045/048 | H13: Not started | I13: Feeds AP-4 / M-12
A14: T-11 | B14: Aggregate | C14: agg.stage_coverage | D14: Country/entity x quarter | E14: ECB SUP / EBA dashboard | F14: scope, quarter, stage1/2/3 share, coverage | G14: S-049/050, AP-3 | H14: Not started | I14: Include NBFC panel here too
A15: T-12 | B15: Aggregate | C15: agg.india_anchor_series + agg.india_geo_panel | D15: Segment/district x period | E15: Long format | F15: state/district, product, PAR/NPA metric, period, value | G15: S-075..S-100 | H15: Not started
A16: T-13 | B16: Aggregate | C16: agg.card_trust_series / agg.pool_series(_india) | D16: Pool x month | E16: 10-D / rationale-derived | F16: pool_id, month, chargeoff, delinq buckets, MPR/CCE, CE | G16: S-009, S-102 | H16: Not started
A17: T-14 | B17: Scenario | C17: scen.macro_paths + scen.climate_paths | D17: Scenario x variable x period | E17: Fed/EBA/BoE/RBI/NGFS | F17: scenario_id, variable, period, value, vintage | G17: S-053/063/071/075 | H17: Not started
A18: T-15 | B18: Index | C18: idx.collateral_indices | D18: Index x geography x period | E18: — | F18: index_id, geo, period, value | G18: S-005/026/088 | H18: Not started | I18: HPI, Manheim, RESIDEX
A19: T-16 | B19: Meta | C19: meta.source_registry + meta.load_log | D19: Source / load event | E19: This workbook | F19: source_id, license, fetch date, rows, QA status | G19: All | H19: Not started | I19: Mirror of 1_Sources for lineage

Sheet 6_Anchors
A1: 6. KEY ANCHOR NUMBERS — calibration reference
A2: Verified headline numbers with as-of dates. These are the targets synthetic books and models must reproduce. Full context in landscape doc.
A3: ID | B3: Theme | C3: Metric | D3: Segment / scope | E3: Value | F3: As-of | G3: Source | H3: Doc ref | I3: Use in models
A4: A-01 | B4: India LGD | C4: IBC recovery rate (realisation vs claims, annual) | D4: India corporate, FY25 | E4: ~37% | F4: FY25 | G4: RBI Trend & Progress (Dec-25) | H4: §4.2 | I4: Corporate LGD by channel
A5: A-02 | B5: India LGD | C5: SARFAESI recovery rate | D5: India, FY25 | E5: 31.5% | F5: FY25 | G5: RBI T&P | H5: §4.2 | I5: Secured retail/SME LGD
A6: A-03 | B6: India LGD | C6: Lok Adalat recovery rate | D6: India, FY25 | E6: 2.4% | F6: FY25 | G6: RBI T&P | H6: §4.2 | I6: Small-ticket LGD
A7: A-04 | B7: India LGD | C7: IBBI cumulative realisation vs admitted claims | D7: India CIRPs, cum. to Mar-26 | E7: 30.6% | F7: Mar-26 | G7: IBBI quarterly newsletter | H7: §4.2 | I7: Corporate LGD level (cutoff-sensitive: 33.7% Jun-25)
A8: A-05 | B8: India LGD | C8: IBBI realisation vs liquidation value / vs fair value | D8: India CIRPs, cum. | E8: 166.9% / 94.6% | F8: Mar-26 | G8: IBBI | H8: §4.2 | I8: Recovery vs collateral-value benchmarks
A9: A-06 | B9: India LGD | C9: Avg time: closed liquidations | D9: India | E9: ~691 days | F9: Mar-26 | G9: IBBI | H9: §4.2 | I9: Discounting/workout duration
A10: A-07 | B10: India LGD | C10: ARC security-receipt cumulative recovery | D10: India SRs | E10: 65-70% FY25E; 75-80% FY26E | F10: Jun-25 | G10: CRISIL SR study | H10: §4.2 | I10: Distressed secondary-market LGD
A11: A-08 | B11: Wholesale LGD | C11: GCD LGD: unsecured / secured | D11: Global wholesale | E11: ~27% / ~22% | F11: 2024 reports | G11: GCD free library | H11: §3.3 | I11: Wholesale LGD priors
A12: A-09 | B12: Wholesale LGD | C12: GCD LGD: senior / subordinated; time-to-recovery | D12: Global wholesale | E12: 26% / 38%; ~1.2y median | F12: 2024 reports | G12: GCD | H12: §3.3 | I12: Seniority splits, timing
A13: A-10 | B13: Wholesale LGD | C13: Banca d'Italia bad-loan recovery rate | D13: Italy, 2024 (series 2006+) | E13: 41% avg (sec 44%, unsec 37%) | F13: Dec-25 note | G13: BdI Notes No. 48 | H13: §3.3 | I13: Workout-LGD time series; downturn evidence
A14: A-11 | B14: Wholesale LGD | C14: NPL sale price vs GBV | D14: Italy sofferenze / other NPE | E14: 24% / 51% | F14: 2024 | G14: BdI No. 48 | H14: §3.3 | I14: Sale-vs-workout discount
... A47: A-44 | B47: Securitisation | C47: India securitisation volume | D47: India, FY26 | E47: Rs 2.55 lakh cr | F47: Apr-26 | G47: CRISIL PR | H47: §4.6 | I47: Pool-data sample size

Sheet 7_Licensing
A1: 7. LICENSING REGISTER — check before you build on it
A2: Summary judgements only — re-read source terms before any external release. Doc §8.
A3: Source group | B3: License / constraint | C3: Prototype use | D3: Commercial product | E3: Redistribution | F3: Notes
A4: Fannie / Freddie / Ginnie | B4: Free; terms restrict redistribution | C4: OK | D4: Review terms | E4: No | F4: Fine for internal prototypes; read terms before publishing derived data
A5: Kaggle competition data (Amex, Home Credit, LTFS mirrors, GMSC) | B5: Competition rules: academic/non-commercial | C5: OK | D5: No (without permission) | E5: No | F5: Prototype & teach yes; productize no
A6: Bondora/Go&Grow, Berka, MIX Market, South German Credit | B6: Open / CC BY 4.0 / research use | C6: OK | D6: Mostly OK (attribute) | E6: CC BY: yes with attribution | F6: MIX & South German are CC BY 4.0
A7: NUS-CRI | B7: Free with credentials; non-commercial only | C7: OK | D7: No (separate arrangement) | E7: No | F7: Commercial use needs agreement
A8: Bureau/industry PDFs (CIBIL, CRIF, MFIN, Sa-Dhan, Equifax, FACE) | B8: Copyrighted reports | C8: OK (model from) | D8: Derived models OK; tables no | E8: No | F8: Don't republish extracted tables
A9: CRA disclosures (Annexure V/VI, studies, rationales) | B9: Public regulatory disclosures | C9: OK | D9: Derived datasets: cite | E9: Avoid wholesale republication | F9: SEBI-mandated transparency
A10: Government/regulator open data (RBI, IBBI, NeSL, CGTMSE, SEC, SBA, Fed, FDIC, NCUA, data.gov.in, IMF, BIS, WB, EBA, ECB) | B10: Public domain / open government | C10: OK | D10: OK | E10: Generally OK (attribute) | F10: The safest layer
A11: GCD / Japan CRD raw pools | B11: Members only (regulated lenders, give-to-get) | C11: Via member bank only | D11: Via member bank only | E11: No | F11: Free summary reports usable as priors
A12: Moody's / S&P / Fitch studies | B12: Copyright; free access | C12: OK (cite) | D12: Cite; don't reproduce tables | E12: No | F12: Digitize numbers with provenance
A13: Moody's DRD / S&P CreditPro / Trepp / LCD / Orbis | B13: Paid licenses | C13: If licensed | D13: If licensed | E13: No | F13: Check WRDS/university access first
A14: CIC defaulter registries (search portals) | B14: Public dissemination, search-only; ToS on scraping | C14: Careful (legal review) | D14: Careful | E14: No bulk republication | F14: Throttled, documented protocol; Experian most tolerant
... A17: P2P platform disclosures | B17: RBI-mandated public disclosure | C17: OK | D17: Cite platform | E17: No | F17: Aggregate series fine

Sheet 8_Watchlist
A1: 8. WATCHLIST — unverified items & upcoming releases
A2: Things to re-check plus the release calendar that should trigger refreshes.
A3: ID | B3: Item | C3: Type | D3: Expected / check date | E3: Action needed | F3: Priority | G3: Status | H3: Notes
A4: W-01 | B4: FSR Jun-2026 adverse-scenario GNPA print (v1 carried 3.8-4.1%) | C4: Unverified | D4: Aug-2026 | E4: Open FSR PDF, confirm adverse GNPA path | F4: P1 | G4: Not started | H4: rbidocs bot-gated - manual download
A5: W-02 | B5: Moody's annual default study 2026 edition (2025 data) | C5: Unverified | D5: Check now | E5: Locate via ratings.moodys.com registration or mirror | F5: P2 | G5: Not started
A6: W-03 | B6: NABARD Status of Microfinance FY25 edition | C6: Unverified | D6: Sep-2026 | E6: Check nabard.org publications | F6: P3 | G6: Not started
A7: W-04 | B7: Equifax India defaulter search portal | C7: Unverified | D7: When needed | E7: Locate portal or confirm absence | F7: P3 | G7: Not started
A8: W-05 | B8: Mintos loan-book export current availability | C8: Unverified | D8: When needed | E8: Login and check export | F8: P3 | G8: Not started
A9: W-06 | B9: ECGC annual-report claims data (export-credit loss proxy) | C9: Unverified | D9: Sep-2026 | E9: Pull latest ECGC AR; extract claims vs premium | F9: P3 | G9: Not started | H9: §5.1 addition
A10: W-07 | B10: ELFA MLFI-25 / Equifax SBLI / KC Fed / Moody's project finance current editions | C10: Unverified (§2.11) | D10: Sep-2026 | E10: Re-verify sources and access | F10: P3 | G10: Not started | H10: Added from coverage audit
A11: W-08 | B11: Fitch study access route (registration) | C11: Unverified | D11: When needed | E11: Register and confirm downloads | F11: P3 | G11: Not started
A12: W-09 | B12: MFIN Micrometer 58 (Q1 FY27) | C12: Upcoming release | D12: ~Sep-2026 | E12: Ingest into PL-26 | F12: P2 | G12: Not started
A13: W-10 | B13: CRISIL default & transition study FY2026 | C13: Upcoming release | D13: ~Dec-2026 | E13: Digitize into anchors | F13: P2 | G13: Not started
A14: W-11 | B14: RBI FSR Dec-2026 | C14: Upcoming release | D14: ~Dec-2026 | E14: Update anchors + scenario annex | F14: P1 | G14: Not started
A15: W-12 | B15: RBI T&P 2025-26 (recovery-by-channel FY26) | C15: Upcoming release | D15: ~Dec-2026 | E15: Update A-01..A-03 | F15: P1 | G15: Not started
A16: W-13 | B16: EBA P3DH full-year 2025 ref-date data + 2026 dates | C16: Upcoming release | D16: H2-2026 | E16: Extend AP-4 panel | F16: P1 | G16: Not started
A17: W-14 | B17: NGFS Phase VI (physical-risk overhaul) | C17: Upcoming release | D17: End-2026 | E17: Re-run climate overlays on Phase VI | F17: P2 | G17: Not started | H17: Time climate work accordingly
A18: W-15 | B18: BoE 2026 desk-based stress test publication | C18: Upcoming release | D18: Q4-2026 | E18: Ingest aggregate results | F18: P3 | G18: Not started
A19: W-16 | B19: EBA Transparency Exercise Dec-2026 | C19: Upcoming release | D19: Dec-2026 | E19: Refresh bank panel | F19: P2 | G19: Not started
A20: W-17 | B20: RBI final Model Risk Management guidance (post-consultation) | C20: Upcoming release | D20: H2-2026? | E20: Align validation-doc templates | F20: P2 | G20: Not started | H20: Draft closed Jul-2026
A21: W-18 | B21: RBI climate disclosure framework finalization / scenario guidance | C21: Upcoming release | D21: Unknown | E21: Track; RB-CRIS phase-2 | F21: P3 | G21: Not started
